spike2py/__init__.py
spike2py/channels.py
spike2py/demo.py
spike2py/plot.py
spike2py/read.py
spike2py/sig_proc.py
spike2py/trial.py
spike2py/types.py
spike2py-0.2.10.dist-info/LICENSE
spike2py-0.2.10.dist-info/METADATA
spike2py-0.2.10.dist-info/WHEEL
spike2py-0.2.10.dist-info/top_level.txt
spike2py-0.2.10.dist-info/RECORD
