Metadata-Version: 2.1
Name: spike2py
Version: 0.2.10
Summary: "Import, parse and process data collected with Spike2".
Home-page: https://github.com/MartinHeroux/spike2py
Author: Martin Heroux
Author-email: "Martin Heroux" <heroux.martin@gmail.com>
License: GPLv3
Classifier: License :: OSI Approved :: GNU General Public License v3 (GPLv3)
Classifier: Programming Language :: Python :: 3
Classifier: Programming Language :: Python :: 3.9
Classifier: Programming Language :: Python :: 3.10
Classifier: Programming Language :: Python :: 3.11
Classifier: Intended Audience :: Science/Research
Requires-Python: >=3.10
License-File: LICENSE
Requires-Dist: numpy <2,>=1.25.0
Requires-Dist: scipy <2,>=1.10.0
Requires-Dist: matplotlib <4,>=3.7.0
